{"ProvinceName":"河北","Citys":[{"Name":"石家庄","LineNames":["1路","10路","11路","12路","13路","14路","15路","16路","17路","18路","19路","101路","102路","103路","106路","107路","108路","110路","111路","112路","113路","115路","116路","117路","118路","130路","131路","132路","133路","134路","135路","136路","137路","138路","139路","140路","142路","143路","145路","147路","148路","150路","164路","171路","177路","192路","1环1路","1环2路","139路区间","东西广场环线","动物园-西杨庄班线","动物园-西部长青班线","3路","30路","31路","32路","33路","34路","35路","36路","37路","38路","39路","301路","302路","303路","304路","305路","306路","307路","308路","309路","310路","311路","312路","313路","314路","315路","316路","317路","318路","319路","320路","321路","322路","323路","325路","326路","327路","328路","331路","333路","339路","344路","347路","357路","368路","304路班线","347路付线","6路","60路","61路","62路","63路","65路","66路","67路","68路","69路","4路","40路","41路","42路","43路","45路","46路","48路","49路","7路","70路","71路","72路","73路","75路","76路","77路","78路","79路","2路","20路","21路","22路","23路","24路","25路","26路","27路","28路","29路","201路","202路","203路","204路","205路","206路","207路","208路","210路","211路","212路","215路","216路","261路","281路","290路","2环1路","2环2路","5路","50路","51路","52路","53路","54路","55路","56路","57路","58路","59路","501路","502路","503路","504路","505路","506路","507路","508路","510路","511路","512路","515路","516路","517路","518路","519路","520路","522路","523路","525路","526路","530路","536路","537路","553路","555路","572路","574路","580路","503路西线","508路付线","504路付线1","504路付线2","前杜北班线","9路","90路","91路","92路","93路","94路","95路","96路","97路","98路","99路","藁城环1路","藁城环2路","宜安-于庄班线","8路","81路","82路","84路","85路","86路","87路","88路","89路","快1路","快32路","快35路","快107路","快177路","快516路","快2环1路","快2环2路","空铁快线","观光3路","旅游1路","旅游2路","旅游3路","旅游5路","旅游6路","旅游7路","旅游11路","旅游12路","鹿泉环1路","鹿泉环2路"]},{"Name":"保定","LineNames":["1路","10路","11路","12路","13路","14路","15路","16路","17路","18路","19路","101路","102路","103路","104路","105路","106路","107路","108路","126路","168路","182路","1335路","10路区间","107路快车(T107)","3路","30路","31路","32路","33路","35路","36路","37路","38路","39路","301路","302路","311路","313路","316路","318路","39路区间","316路(樊村)","316路支线(义联庄)","316路支线(白岭村)","2路","20路","21路","22路","23路","24路","25路","26路","27路","28路","29路","201路","202路","203路","204路","205路","206路","207路","208路","209路","212路","23路快车(T23)","27路(保定东站)","5路","50路","51路","52路","53路","55路","56路","57路","59路","501路","505路","51路区间","502路(一工厂)","502路(二工厂)","502路(冲焊园)","58路(1月23日起停运)","7路","70路","4路","43路","4路夜间","8路","801路","806路","808路","838路","838松林店班车","838高碑店班车","9路","902路","903路","912路","921路","922路","941路","946路","951路","961路","971路","981路","981早班","917路快车","917路野三坡专线","6路","60路","61路","62路","63路","65路","66路","67路","68路","69路","601路","602路","607路","608路","609路","610路","612路","613路","616路","621路","631路","655路","656路","661路","671路","672路","681路","691路","621路区间","641路容城","641路白沟","608路(河图)","608路(建国路)","656白洋淀专线","602路(大午温泉)","安国801路","安国802路","安国803路","安国805路","安国816路","定兴1路","定兴2路","定兴3路","定兴5路","定兴6路","定兴8路","定兴9路","定州1路","定州2路","定州5路","定州6路","定州8路","定兴11路","定兴12路","定兴13路","定兴15路","定兴16路","定兴18路","定兴19路","定兴20路","定兴21路","定兴22路","定兴23路","定兴-兰沟","定兴-容城","定兴-富位","定兴-杨村","定兴-白沟","定兴-石柱","定兴-石象","定兴-谭城","定兴-青中","定州-阜平","大王店201路","大王店202路","大王店203路","定兴-五柳庄","定兴-太平庄","定兴-长安城","定州3路北线","定州3路南线","定州9路环线","满城3路","满城4路","满城6路","满城7路","满城8路","满城9路","满城10路","满城12路","容城101路","容城102路","容城103路","容城105路","容城106路","涞水1路","涞水2路","涞水3路","涞水6路","涞水7路","顺平1路","涞水12路","涞水22路","三台-徐水","涞水-野三坡","涞水-六里桥班车","石家庄机场保定线","石家庄机场高阳线","市民服务中心接驳车","石家庄机场定州安国线","石家庄机场容城白沟线","市民服务中心1号游览专线","曲阳1路","曲阳2路","曲阳3路","曲阳5路","曲阳6路","曲阳7路","曲阳8路","曲阳9路","清苑1路","清苑2路","清苑3路","清苑5路","清苑8路","清苑9路","清苑10路","清苑11路","清苑12路","清苑16路","清苑18路","清苑22路","清苑28路","曲阳102路","曲阳106路","曲阳107路","清苑101路","清苑102路","清苑103路","清苑105路","清苑106路","清苑107路","清苑-东吕","清西陵易水湖专线","徐水2路","徐水3路","徐水4路","徐水5路","徐水7路","徐水8路","徐水9路","雄安16路","徐水101路","徐水102路","徐水103路","徐水105路","徐水106路","徐水107路","徐水108路","蠡县101路","蠡县102路","蠡县103路","蠡县105路","蠡县107路","蠡县108路","蠡县109路","雄县102路","雄县103路","雄县104路","雄县105路","雄县106路","雄县201路","雄安新1路","雄安新2路","徐水1路支1路","徐水1路支2路","雄安公交1号线","雄县-赵公口班车","雄安新区至狼牙山直通车","雄安新区定制班车(保定-雄安)","游1路","游2路","游3路","游5路","涞源2路","涞源3路","涞源4路","涞源6路","涞源7路","涞源8路","涞源9路","涞源10路","涞源11路","涞源12路","涞源14路","涞源15路","涞源18路","野三坡专线","涞源(东线)-保定","涞源(钢厂)-保定","狼牙山专线","涿州2路","涿州3路","涿州4路","涿州5路","涿州6路","涿州7路","涿州11路","涿州12路","涿州13路","涿州15路","涿州16路","涿州18路","涿州20路","涿州21路","涿州23路","涿州25路","涿州26路","涿州2路支","涿州1路区间","涿州1路环线","涿州8路(跨省)","涿州9路(跨省)","涿州10路(停运)","涿州19路(跨省)","涿州22路(跨省)","涿州1路支线(里渠)","涿州19路支线(跨省)","阜平101路","阜平102路","阜平103路","阜平201路","阜平202路","阜平203路","阜平204路","阜平205路","阜平206路","阜平207路","凤凰山专线","K1路","K2路","K1路夜间","特1路","特2路","特3路","特4路","唐县1路","唐县2路","唐县3路","唐县5路","唐县6路","唐县7路","唐县8路","唐县9路","唐县11路","唐县12路","天生桥专线","唐县-夹子(12支线)","唐县-花塔(12支线)","唐县-贤表(11支线)","唐县-黄岩(11支线)","唐县-大石峪(12支线)","G1路","G3路","G6路","G2L路","G2S路","G3路区间1","G3路区间2","G3路区间3","G6路区间1","G6路区间2","高阳101路","高阳102路","高阳103路","高阳104路","高碑店-六里桥班车","博野2路","白沟101路","白沟102路","白沟103路","白沟104路","白沟105路","保定-三台","保定-李庄","保定-涞水","保定-管头","保定-蠡县","保定-阳城","保定-顺平","白沟-昝岗","白石山专线","保定-付家营","保定-北段庄","保定-大杨庄","博野1路环线","保定-大李各庄","保定-开口(高速)","保定-昝岗(高速)","保定-野北(高速)","白洋淀景区1号线","白洋淀景区2号线","保定-大茂山(高速)","保定-奇峰塔(高速)","北京大兴机场保定线","北京首都机场保定线"]},{"Name":"唐山","LineNames":["1路","10路","11路","12路","13路","14路","15路","16路","17路","18路","101路","102路","103路","104路","105路","106路","108路","109路","110路","111路","112路","113路","114路","116路","117路","118路","17路支","118路支","114路快车","3路","30路","32路","35路","36路","37路","38路","39路","32路支","5路","50路","51路","52路","53路","54路","55路","56路","57路","59路","51路区间","58路(已停运)","2路","20路","21路","22路","23路","25路","26路","27路","28路","29路","201路","202路","203路","204路","205路","207路","208路","209路","210路","211路","212路","213路","214路","215路","216路","218路","219路","220路","29路区间","8路","80路","84路","87路","88路","89路","80路支","4路","41路","42路","43路","44路","45路","46路","47路","48路","44路支","6路","60路","61路","62路","64路","66路","67路","68路","69路","9路","90路","91路","92路","94路","95路","98路","99路","D01路","D02路","D03路","D01路支","丰润1路","丰润2路","丰润3路","丰润4路","丰润5路","丰润6路","丰南商务专线","凤凰花卉专线1路","凤凰花卉专线2路","7路","76路","77路","78路","79路","79路区间","直达1路","游1路","游2路","游3路","游5路","游6路","游7路","游1路区间","K2路","K3路"]},{"Name":"廊坊","LineNames":["10路","11路","12路","14路","16路","17路","18路","19路","1路A线","1路B线","13路A线","13路B线","15路A线","15路B线","5路","3路","31路","32路","33路","34路","35路","36路","37路","30路A线","30路B线","38路A线","38路B线","2路","21路","22路","23路","24路","25路","27路","28路","29路","20路A线","20路B线","26路A线","26路B线","4路","4路空港","7路","9路A线","9路B线","6路","大厂1路","大厂2路","大厂3路","大厂4路","大城101路","大城102路","大城103路","大厂环城A线","大厂环城B线","大厂潮白工业园区A线","大厂潮白工业园区B线","大兴机场巴士[廊坊线]","霸州1路","霸州2路","霸州3路","霸州4路","霸州5路","霸州6路","霸州7路","霸州8路","霸州9路","北京四惠","北京六里桥","北京木樨园","三河101路","三河102路","三河103路","三河104路","三河105路","三河201路","三河202支","三河202路","三河203路","三河301路","三河302路","三河303路","三河304支","三河304路","三河307路","三河308路","三河401路","三河501路","三河503路","三河505路","三河509支","三河509路","石家庄[固安/涿州]","石家庄[永清/霸州]","首都机场巴士[廊坊线]","天津通莎","文安1路","文安2路","8路","805快","805路","826路","香河201支","香河201路","香河202路","香河203路","香河204路","香河205路","香河207路","香河208路","香河210路","香河211路","香河1路内环","香河1路外环"]},{"Name":"张家口","LineNames":["18路 公安大厦—平门","19路 邮电楼—鹄突地","13路 口里东窑子—五墩","1路[崇礼区]二道沟环线","1路[张北县]蔬菜城-西梁","1路 张家口南站—明德北","12路 北环路口—第二医院","102路 平门—宣化客运中心","108路 气象局—泰诺安公司","1路[宣化区]宣化站—化工厂","103路 宣化滨河路—古宏庙街","107路 宣化滨河路—宁远机场","109路 许家庄—金隅水泥北门","1路[怀安县]汽车站-古堡新城","11路 帝达世博广场—职教中心","1路[万全区]李青庄—通远驾校","1路[崇礼区]二道沟—希望小学","16路 西甸子—北站(长青路单行)","15路[宣化区]体育场—崞村(西线)","16路[宣化区]体育场—崞村(东线)","101路 张家口南站—张北南环路口","1路[尚义县]新车站—新华街村委会","15路 钻石南路北口—东山高新开发区","106路 宣化北高速口—张家口客运南站","10路[宣化区]河子西环线(第五中学方向)","11路[宣化区]河子西环线(第二中学方向)","1路[涿鹿县]轩园大酒店—保岱镇窑子头","10路 长途汽车站—张家口南站(沙岭子西站)","32路 正沟—赐儿山","34路 通泰桥-新兴苑","31路 西泽园—东麓苑","301路通泰桥-南兴渠村","36路 林里嘉苑—张家坊","32路支线 南天门—赐儿山","36路支线红旗楼-张家坊村","39路 姚家房—宣化体育场东","3路[万全区]东红庙—吴家窑","3路[宣化区]宣化站—北门口","3路[尚义县]新车站—汽车站","36路支线 通泰家居城-张家坊","36路[宣化区] 盆窑村—大慢岭","3路 钻石南路北口—职教中心","33路 帝达世博广场—火车北站","35路 林里嘉苑—西豪丽景小区","37路 林里嘉苑—北方花木基地","38路 祭风台—闫家屯(金鸿能源)","33路[宣化区]上古现代城—杨家营","5路[宣化区]宣化站—马家湾","5路[怀安县]汽车站—沙家屯","5路 张家口学院西—栖凤谷小区","2路 平门—城管执法局","2路[怀安县]交通局-汽车站","21路 红旗楼—宣化客运中心","2路[宣化区]河子西—侯家庙","23路 百货大楼—宁远机场航站楼","21路[宣化区]建国街小学—红旗楼","2路[尚义县]新车站-尚义县总商会","202路 西沙河汽车站—柴沟堡汽车站","23路[宣化区]宣化客运中心—庞家堡","8路[张北县]内环","8路 展览馆-镇朔楼","8路[宣化区]北门口—小慢岭","8路[崇礼区]区政府—区人民医院","899路 下花园—北京朱辛庄公交场站","880路 怀来沙城客运站—北京地铁朱辛庄站","4路 展览馆—燕兴机械厂","4路[怀安县]汽车站-西沙洼","4路[宣化区]宣化站—江家屯","9路 东方苑—赐儿山","9路[宣化区]御府天苑—北门口","6路 张家口学院西—口里东窑子","6路[宣化区]福田重机—西城垣公园","K1路 展览馆—张家口站(高铁)","7路 展览馆—华联超市","7路[宣化区]泥河子小学—下八里","[宣化区]假日绿岛旅游专线","[宣化区]黄羊山文化园旅游专线","特1路[宣化区]南门口-钟楼","特2路[宣化区]小东门南-大新门南","特1路明德北—张家口南站(沙岭子西站)","特11路 职教中心—张家口南站(沙岭子西站)","游1路 公交总公司—明湖","首都机场巴士"]},{"Name":"承德","LineNames":["1路","11路","12路","13路","15路","16路","17路","19路","118路","10路区间","11路区间","15路区间","18路快线","118路支线","30路","31路","32路","33路","34路","35路","36路","37路","39路","3-1路","2路","20路","21路","22路","23路","24路","25路","27路","28路","22路支线","29路区间","29路支线","6路","60路","61路","67路","68路","69路","8路","801路","5路","50路","51路","52路","53路","55路","56路","57路","58路","501路","502路","503路","504路","505路","506路","507路","5路区间","50路区间","51路支线","9路","901路","902路","9路区间","承德县1路","承德县2路","承德县3路","承德县5路","承德县6路","承德县城际1路","7路","7路区间","地铁望京西站—兴隆公交总站","地铁望京西站—滦平公交总站","地铁望京西站—丰宁炫靓建材城","K1路","滦平县1路","滦平县2路","隆化县1路","隆化县2路","隆化县3路","丰宁县102路","丰宁县103路","丰宁县106路","丰宁县远郊1路","丰宁县远郊2路","丰宁县远郊3路","丰宁县远郊5路","丰宁县远郊8路","丰宁县101路支线","平泉市1路","平泉市2路","平泉市3路","平泉市5路","平泉市6路","平泉市7路","平泉市10路","平泉市201路","平泉市202路","平泉市202路支线","游1路","鹰手营子区1路"]},{"Name":"沧州","LineNames":["10路","11路","13路","14路","16路","17路","18路","19路","138路","1路(大公共)","1路(小公共)","3路","31路","306路","307路","332路","505路","526路","528路","539路","21路","22路","23路","29路","219路","226路","8路","402路","420路","430路","9路","特5路","特7路","604路","612路","615路"]},{"Name":"秦皇岛","LineNames":["1路","10路","11路","12路","13路","14路","15路","16路","17路","18路","19路","19路夜班线路","7路","701路","2路","20路","21路","22路","23路","24路","25路","26路","27路","28路","29路","24路支线","26路支线","3路","30路","31路","32路","33路","34路","35路","36路","37路","302路","33路支线","31路夜班线路","32路夜班线路","5路","4路","6路","601路","602路","603路","605路","8路","8路夜班线路","9路","901路","902路","903路","905路","专线2路","专线3路","专线4路","专线5路"]},{"Name":"衡水","LineNames":["20路","21路","26路","2路(直)","2路(绕)","4路","3路","102","1路","10路","11路","12路","13路","14路","15路","16路","17路","18路","19路","6路","7路","9路","5路","8路"]},{"Name":"邢台","LineNames":["1路","10路","11路","12路","13路","14路","15路","16路","17路","18路","19路","101路","102路","103路","104路","105路","106路","108路","109路","111路","113路","10路区间","3路","30路","31路","32路","33路","34路","35路","36路","37路","38路","306路","311路","312路","313路","314路","315路","316路","317路","6路","2路","20路","21路","22路","23路","24路","25路","26路","27路","28路","29路","211路","任县301路","任县302路","任县303路","任县304路","任县305路","任县307路","任县308路","任县309路","任县310路","9路","901路","4路","40路","42路","南和201路","南和202路","南和203路","南和204路","南和205路","南和206路","南和207路","南和208路","南和209路","南和210路","7路","8路"]},{"Name":"邯郸","LineNames":["1路","11路","12路","13路","15路","16路","17路","19路","15路支线","3路","30路","31路","32路","33路","34路","36路","38路","39路","301路","305路","316路","39路支线","5路","50路","51路","52路","53路","55路","56路","57路","58路","59路","5路夜班","20路","21路","23路","24路","25路","26路","28路","29路","21路夜班","27路(原201路)","9路","901路","902路(跨省)","6路","60路","62路","63路","64路","65路","66路","67路","68路","604路(游4路)","605路(游5路)","4路","40路","42路","44路","45路","46路","49路","4路支线","成安—高铁站线","7路","70路","71路","76路","77路","7路支线","70路支线","峰峰1路","峰峰9路","峰峰12路","峰峰19路","峰峰1路支线","8路","80路","801路","805路","806路","809路","811路","812路","813路","816路","810西路","803路(107国道)","802路(中华大街)","808北路(309国道)","808南路(邯武快速路)","高铁站—市委党校线","环202路","环204路","环205路","邯矿总医院定制专线","邯郸学院—佛山动物园线","永年66路","永年—高铁站线","K5路大站快车","武安1路","武安2路","武安4路","武安6路","武安8路","武安9路","武安12路","武安13路","武安20路","武安29路","武安55路","武安58路(旅游专线)"]},{"Name":"迁安","LineNames":["1路","12路","13路","14路","15路","16路","17路","2路","5路","3路","4路","6路","8路","9路","7路"]},{"Name":"武安","LineNames":["1路","11路","12路","8路","3路","4路","2路","6路","9路"]}]}